LICENSE
MANIFEST.in
README.rst
setup.cfg
setup.py
src/sentry_top/__init__.py
src/sentry_top/models.py
src/sentry_top/plugin.py
src/sentry_top.egg-info/PKG-INFO
src/sentry_top.egg-info/SOURCES.txt
src/sentry_top.egg-info/dependency_links.txt
src/sentry_top.egg-info/entry_points.txt
src/sentry_top.egg-info/not-zip-safe
src/sentry_top.egg-info/requires.txt
src/sentry_top.egg-info/top_level.txt
src/sentry_top/management/__init__.py
src/sentry_top/management/commands/__init__.py
src/sentry_top/management/commands/top.py