Metadata-Version: 1.1
Name: sentry-top
Version: 0.1.0
Summary: A Sentry extension which tracks the most active projects
Home-page: http://github.com/getsentry/sentry-top
Author: David Cramer
Author-email: dcramer@gmail.com
License: Apache License 2.0
Platform: UNKNOWN
Classifier: Framework :: Django
Classifier: Intended Audience :: Developers
Classifier: Intended Audience :: System Administrators
Classifier: Operating System :: OS Independent
Classifier: Topic :: Software Development
